<?xml version="1.0" encoding="UTF-8"?>
<!DOCTYPE xkbConfigRegistry SYSTEM "xkb.dtd">
<xkbConfigRegistry version="1.1">
  <layoutList>
    <layout>
      <configItem>
        <name>workman</name>
        <shortDescription>en</shortDescription>
        <description>English (Workman, ääkköset)</description>
        <countryList>
          <iso3166Id>US</iso3166Id>
        </countryList>
        <languageList>
          <iso639Id>eng</iso639Id>
        </languageList>
      </configItem>
    </layout>
  </layoutList>
</xkbConfigRegistry>
